setup.py
amazonreviewanalyzer_preprocess/__init__.py
amazonreviewanalyzer_preprocess/csvreader.py
amazonreviewanalyzer_preprocess/csvwriter.py
amazonreviewanalyzer_preprocess/review.py
amazonreviewanalyzer_preprocess.egg-info/PKG-INFO
amazonreviewanalyzer_preprocess.egg-info/SOURCES.txt
amazonreviewanalyzer_preprocess.egg-info/dependency_links.txt
amazonreviewanalyzer_preprocess.egg-info/requires.txt
amazonreviewanalyzer_preprocess.egg-info/top_level.txt