Metadata-Version: 1.1
Name: amazonreviewanalyzer-preprocess
Version: 0.1.dev267780807
Summary: Preprocessing utilities for the package amazonreviewanalyzer
Home-page: https://gitlab.informatik.uni-bremen.de/sliedtke/amazonreviewanalyzer-preprocess
Author: Simon Liedtke
Author-email: sliedtke@uni-bremen.de
License: UNKNOWN
Platform: UNKNOWN
Classifier: Development Status :: 3 - Alpha
Classifier: Programming Language :: Python :: 3
Classifier: Programming Language :: Python :: 3.4
Classifier: Topic :: Text Processing
